odoo/addons/product_feeder_id/LICENSE
odoo/addons/product_feeder_id/README.rst
odoo/addons/product_feeder_id/__init__.py
odoo/addons/product_feeder_id/__manifest__.py
odoo/addons/product_feeder_id/images/screen.png
odoo/addons/product_feeder_id/models/__init__.py
odoo/addons/product_feeder_id/models/product_template.py
odoo/addons/product_feeder_id/static/description/icon.png
odoo/addons/product_feeder_id/static/description/index.html
odoo/addons/product_feeder_id/tests/TEST_INSTRUCTIONS.rst
odoo/addons/product_feeder_id/views/product_template.xml
odoo_addon_product_feeder_id-16.0.1.0.0.dist-info/METADATA
odoo_addon_product_feeder_id-16.0.1.0.0.dist-info/WHEEL
odoo_addon_product_feeder_id-16.0.1.0.0.dist-info/top_level.txt
odoo_addon_product_feeder_id-16.0.1.0.0.dist-info/RECORD
